Metadata-Version: 2.1
Name: djangocms-forms-maintained
Version: 202206141440
Summary: The easiest and most flexible Django CMS Form builder w/ ReCaptcha v2 support!
Home-page: https://github.com/avryhof/djangocms-forms
Author: Amos Vryhof,Mishbah Razzaque
Author-email: amos@vryhofresearch.com,mishbahx@gmail.com
License: BSD
Project-URL: Original Project, https://github.com/mishbahr/djangocms-forms
Project-URL: GitHub Repo, https://github.com/avryhof/djangocms-forms
Project-URL: Bug Tracker, https://github.com/avryhof/djangocms-forms/issues
Keywords: djangocms-forms-maintained
Classifier: Development Status :: 4 - Beta
Classifier: Framework :: Django
Classifier: Intended Audience :: Developers
Classifier: License :: OSI Approved :: BSD License
Classifier: Natural Language :: English
Classifier: Programming Language :: Python :: 2
Classifier: Programming Language :: Python :: 2.6
Classifier: Programming Language :: Python :: 2.7
Classifier: Programming Language :: Python :: 3
Classifier: Programming Language :: Python :: 3.3
License-File: LICENSE
License-File: AUTHORS.rst
Requires-Dist: django-appconf
Requires-Dist: django-ipware
Requires-Dist: django-recaptcha
Requires-Dist: jsonfield
Requires-Dist: unidecode
Requires-Dist: tablib[xlsx,yaml]
Requires-Dist: hashids
Requires-Dist: requests
Requires-Dist: django-cms (>=3.0)
